{
	"dataList": [
		{
			"index": 0,
			"name": "식량 1",
			"startTime": "REST",
			"duration": "ONCE",
			"restore": "false",
			"effectIndexList": [
				26
			],
			"amountList": [
				1
			],
			"price": 2,
			"tag": "FOOD",
			"script": "음식, 휴식 때 먹어 배고픔을 회복시킵니다."
		},
		{
			"index": 1,
			"name": "식량 2",
			"startTime": "REST",
			"duration": "ONCE",
			"restore": "false",
			"effectIndexList": [
				26
			],
			"amountList": [
				2
			],
			"price": 4,
			"tag": "FOOD",
			"script": "음식, 휴식 때 먹어 배고픔을 회복시킵니다."
		},
		{
			"index": 2,
			"name": "식량 3",
			"startTime": "REST",
			"duration": "ONCE",
			"restore": "false",
			"effectIndexList": [
				26
			],
			"amountList": [
				3
			],
			"price": 6,
			"tag": "FOOD",
			"script": "음식, 휴식 때 먹어 배고픔을 회복시킵니다."
		},
		{
			"index": 3,
			"name": "식량 4",
			"startTime": "REST",
			"duration": "ONCE",
			"restore": "false",
			"effectIndexList": [
				26
			],
			"amountList": [
				4
			],
			"price": 8,
			"tag": "FOOD",
			"script": "음식, 휴식 때 먹어 배고픔을 회복시킵니다."
		},
		{
			"index": 4,
			"name": "따뜻한 우유",
			"startTime": "REST",
			"duration": "ONCE",
			"restore": "false",
			"effectIndexList": [
				0
			],
			"amountList": [
				1
			],
			"price": 2,
			"tag": "NULL",
			"script": "휴식 때 먹어 체력을 1회복시킵니다."
		},
		{
			"index": 5,
			"name": "따뜻한 고급우유",
			"startTime": "REST",
			"duration": "ONCE",
			"restore": "false",
			"effectIndexList": [
				0
			],
			"amountList": [
				2
			],
			"price": 4,
			"tag": "NULL",
			"script": "휴식 때 먹어 체력을 2회복시킵니다."
		},
		{
			"index": 6,
			"name": "베게",
			"startTime": "REST",
			"duration": "EQUIP",
			"restore": "false",
			"effectIndexList": [
				0
			],
			"amountList": [
				1
			],
			"price": 4,
			"tag": "NULL",
			"script": "휴식 때 체력을 1회복시킵니다."
		},
		{
			"index": 7,
			"name": "상처약",
			"startTime": "NOW",
			"duration": "ONCE",
			"restore": "false",
			"effectIndexList": [
				0
			],
			"amountList": [
				1
			],
			"price": 3,
			"tag": "NULL",
			"script": "언제든지 사용하는 즉시 1체력을 회복합니다."
		},
		{
			"index": 8,
			"name": "고급 상처약",
			"startTime": "NOW",
			"duration": "ONCE",
			"restore": "false",
			"effectIndexList": [
				0
			],
			"amountList": [
				2
			],
			"price": 6,
			"tag": "NULL",
			"script": "언제든지 사용하는 즉시 2체력을 회복합니다."
		},
		{
			"index": 9,
			"name": "작업용 장갑",
			"startTime": "TEST",
			"duration": "EQUIP",
			"restore": "true",
			"effectIndexList": [
				27
			],
			"amountList": [
				1
			],
			"price": 5,
			"tag": "NULL",
			"script": "힘을 1올립니다."
		},
		{
			"index": 10,
			"name": "공구벨트",
			"startTime": "TEST",
			"duration": "EQUIP",
			"restore": "true",
			"effectIndexList": [
				27
			],
			"amountList": [
				1
			],
			"price": 5,
			"tag": "NULL",
			"script": "힘을 1올립니다."
		},
		{
			"index": 11,
			"name": "작업용 조끼",
			"startTime": "TEST",
			"duration": "EQUIP",
			"restore": "true",
			"effectIndexList": [
				27
			],
			"amountList": [
				1
			],
			"price": 5,
			"tag": "NULL",
			"script": "힘을 1올립니다."
		},
		{
			"index": 12,
			"name": "1회용 목장갑",
			"startTime": "TEST",
			"duration": "ONCE",
			"restore": "true",
			"effectIndexList": [
				27
			],
			"amountList": [
				1
			],
			"price": 2,
			"tag": "NULL",
			"script": "검사할 때 사용하면 힘을 1올립니다."
		},
		{
			"index": 13,
			"name": "1회용 코팅장갑",
			"startTime": "TEST",
			"duration": "ONCE",
			"restore": "true",
			"effectIndexList": [
				27
			],
			"amountList": [
				1
			],
			"price": 2,
			"tag": "NULL",
			"script": "검사할 때 사용하면 힘을 1올립니다."
		},
		{
			"index": 14,
			"name": "얇은 복장",
			"startTime": "TEST",
			"duration": "EQUIP",
			"restore": "true",
			"effectIndexList": [
				28
			],
			"amountList": [
				1
			],
			"price": 5,
			"tag": "NULL",
			"script": "민첩을 1올립니다."
		},
		{
			"index": 15,
			"name": "운동화",
			"startTime": "TEST",
			"duration": "EQUIP",
			"restore": "true",
			"effectIndexList": [
				28
			],
			"amountList": [
				1
			],
			"price": 5,
			"tag": "NULL",
			"script": "민첩을 1올립니다."
		},
		{
			"index": 16,
			"name": "편안한 의복",
			"startTime": "TEST",
			"duration": "EQUIP",
			"restore": "true",
			"effectIndexList": [
				28
			],
			"amountList": [
				1
			],
			"price": 5,
			"tag": "NULL",
			"script": "민첩을 1올립니다."
		},
		{
			"index": 17,
			"name": "이온음료",
			"startTime": "TEST",
			"duration": "ONCE",
			"restore": "true",
			"effectIndexList": [
				28
			],
			"amountList": [
				1
			],
			"price": 5,
			"tag": "NULL",
			"script": "검사할 때 사용하면 민첩을 1올립니다."
		},
		{
			"index": 18,
			"name": "깨끗한 물",
			"startTime": "TEST",
			"duration": "ONCE",
			"restore": "true",
			"effectIndexList": [
				28
			],
			"amountList": [
				1
			],
			"price": 5,
			"tag": "NULL",
			"script": "검사할 때 사용하면 민첩을 1올립니다."
		},
		{
			"index": 19,
			"name": "손목시계",
			"startTime": "TEST",
			"duration": "EQUIP",
			"restore": "true",
			"effectIndexList": [
				30
			],
			"amountList": [
				1
			],
			"price": 5,
			"tag": "NULL",
			"script": "재주를 1올립니다."
		},
		{
			"index": 20,
			"name": "깔끔한 의복",
			"startTime": "TEST",
			"duration": "EQUIP",
			"restore": "true",
			"effectIndexList": [
				30
			],
			"amountList": [
				1
			],
			"price": 5,
			"tag": "NULL",
			"script": "재주를 1올립니다."
		},
		{
			"index": 21,
			"name": "중국어 사전",
			"startTime": "TEST",
			"duration": "EQUIP",
			"restore": "true",
			"effectIndexList": [
				30
			],
			"amountList": [
				1
			],
			"price": 5,
			"tag": "NULL",
			"script": "재주를 1올립니다."
		},
		{
			"index": 22,
			"name": "구강청정제",
			"startTime": "TEST",
			"duration": "ONCE",
			"restore": "true",
			"effectIndexList": [
				30
			],
			"amountList": [
				1
			],
			"price": 5,
			"tag": "NULL",
			"script": "검사할 때 사용하면 재주을 1올립니다."
		},
		{
			"index": 23,
			"name": "껌",
			"startTime": "TEST",
			"duration": "ONCE",
			"restore": "true",
			"effectIndexList": [
				30
			],
			"amountList": [
				1
			],
			"price": 5,
			"tag": "NULL",
			"script": "검사할 때 사용하면 재주을 1올립니다."
		},
		{
			"index": 24,
			"name": "안경",
			"startTime": "TEST",
			"duration": "EQUIP",
			"restore": "true",
			"effectIndexList": [
				29
			],
			"amountList": [
				1
			],
			"price": 5,
			"tag": "NULL",
			"script": "집중을 1올립니다."
		},
		{
			"index": 25,
			"name": "책",
			"startTime": "TEST",
			"duration": "EQUIP",
			"restore": "true",
			"effectIndexList": [
				29
			],
			"amountList": [
				1
			],
			"price": 5,
			"tag": "NULL",
			"script": "집중을 1올립니다."
		},
		{
			"index": 26,
			"name": "이어플러그",
			"startTime": "TEST",
			"duration": "EQUIP",
			"restore": "true",
			"effectIndexList": [
				29
			],
			"amountList": [
				1
			],
			"price": 5,
			"tag": "NULL",
			"script": "집중을 1올립니다."
		},
		{
			"index": 27,
			"name": "커피",
			"startTime": "TEST",
			"duration": "ONCE",
			"restore": "true",
			"effectIndexList": [
				29
			],
			"amountList": [
				1
			],
			"price": 2,
			"tag": "NULL",
			"script": "검사할 때 사용하면 집중을 1올립니다."
		},
		{
			"index": 28,
			"name": "에너지 드링크",
			"startTime": "TEST",
			"duration": "ONCE",
			"restore": "true",
			"effectIndexList": [
				29
			],
			"amountList": [
				1
			],
			"price": 2,
			"tag": "NULL",
			"script": "검사할 때 사용하면 집중을 1올립니다."
		},
		{
			"index": 29,
			"name": "뇌물 제공-1",
			"startTime": "NOW",
			"duration": "ONCE",
			"restore": "false",
			"effectIndexList": [
				18
			],
			"amountList": [
				1
			],
			"price": 8,
			"tag": "NULL",
			"script": "얻는 즉시 가장 가까운 곳의 공안을 제거합니다."
		},
		{
			"index": 30,
			"name": "뇌물 제공-2",
			"startTime": "NOW",
			"duration": "ONCE",
			"restore": "false",
			"effectIndexList": [
				20
			],
			"amountList": [
				1
			],
			"price": 6,
			"tag": "NULL",
			"script": "얻는 즉시 무작위 공안을 제거합니다."
		},
		{
			"index": 31,
			"name": "레몬에이드",
			"startTime": "NOW",
			"duration": "ONCE",
			"restore": "false",
			"effectIndexList": [
				56
			],
			"amountList": [
				6
			],
			"price": 4,
			"tag": "NULL",
			"script": "얻는 즉시 상쾌함상태를 얻습니다."
		},
		{
			"index": 32,
			"name": "초콜릿",
			"startTime": "NOW",
			"duration": "ONCE",
			"restore": "false",
			"effectIndexList": [
				56
			],
			"amountList": [
				8
			],
			"price": 4,
			"tag": "NULL",
			"script": "얻는 즉시 집중상태를 얻습니다."
		},
		{
			"index": 33,
			"name": "붕대",
			"startTime": "NOW",
			"duration": "ONCE",
			"restore": "false",
			"effectIndexList": [
				57
			],
			"amountList": [
				1
			],
			"price": 4,
			"tag": "NULL",
			"script": "얻은 즉시 다리부상상태를 치유합니다."
		},
		{
			"index": 34,
			"name": "불안장애약",
			"startTime": "NOW",
			"duration": "ONCE",
			"restore": "false",
			"effectIndexList": [
				57
			],
			"amountList": [
				2
			],
			"price": 4,
			"tag": "NULL",
			"script": "얻은 즉시 불안상태를 치유합니다."
		},
		{
			"index": 35,
			"name": "피로회복제",
			"startTime": "NOW",
			"duration": "ONCE",
			"restore": "false",
			"effectIndexList": [
				57
			],
			"amountList": [
				4
			],
			"price": 4,
			"tag": "NULL",
			"script": "얻은 즉시 피곤함상태를 치유합니다."
		},
		{
			"index": 36,
			"name": "채집도구",
			"startTime": "TEST",
			"duration": "EQUIP",
			"restore": "true",
			"effectIndexList": [
				3
			],
			"amountList": [
				1
			],
			"price": 4,
			"tag": "NULL",
			"script": "산에서 주사위 하나를 얻습니다."
		},
		{
			"index": 37,
			"name": "멋드러진 옷",
			"startTime": "TEST",
			"duration": "EQUIP",
			"restore": "true",
			"effectIndexList": [
				2
			],
			"amountList": [
				1
			],
			"price": 4,
			"tag": "NULL",
			"script": "대도시에서 주사위 하나를 얻습니다."
		},
		{
			"index": 38,
			"name": "조선인 쉼터 회워권",
			"startTime": "REST",
			"duration": "ONCE",
			"restore": "false",
			"effectIndexList": [
				0
			],
			"amountList": [
				2
			],
			"price": 3,
			"tag": "NULL",
			"script": "쉼터에 가서 휴식을 취합니다. 휴식 때 체력을 2회복시킵니다."
		}
	]
}